[
  {
    "Name": "name",
    "EMail": "email@gmail.com",
    "Password": "password",
    "_PrivateOrCorporation": 0,
    "_AccountType": 0,
    "CVR": "cvr",
    "Address": "AAA vej, 4000 Roskilde",
    "Country": "Danmark",
    "PhoneNumber": "\u002B45 10 02 24 90",
    "WantsNewsLetter": false,
    "Receipts": [],
    "UsedCoupons": []
  },
  {
    "Name": "name2",
    "EMail": "email2@gmail.com",
    "Password": "pass",
    "_PrivateOrCorporation": 0,
    "_AccountType": 0,
    "CVR": "cvr",
    "Address": "BBB vej, 4000 Roskilde",
    "Country": "Danmark",
    "PhoneNumber": "\u002B45 15 22 42 09",
    "WantsNewsLetter": false,
    "Receipts": [],
    "UsedCoupons": []
  },
  {
    "Name": "ajidao jioadj",
    "EMail": "aabb@gmail.com",
    "Password": "iojad",
    "_PrivateOrCorporation": 0,
    "_AccountType": 0,
    "CVR": "913",
    "Address": "sadjjga 47",
    "Country": "Danmark",
    "PhoneNumber": "\u002B45 12341296",
    "WantsNewsLetter": false,
    "Receipts": [],
    "UsedCoupons": []
  },
  {
    "Name": "akdml adkml",
    "EMail": "ajiod@gmail.com",
    "Password": "jiodjaiodjao",
    "_PrivateOrCorporation": 0,
    "_AccountType": 0,
    "CVR": null,
    "Address": "ianosd 9218, 4000 Roskilde",
    "Country": "Danmark",
    "PhoneNumber": "\u002B45 14587428",
    "WantsNewsLetter": false,
    "Receipts": [],
    "UsedCoupons": []
  },
  {
    "Name": "Frederik Nicolajsen",
    "EMail": "drageon@live.dk",
    "Password": "qwerty",
    "_PrivateOrCorporation": 0,
    "_AccountType": 0,
    "CVR": "123412341234",
    "Address": "Banebrinken, 2400 K\u00F8benhavn NV",
    "Country": "Denmark",
    "PhoneNumber": "\u002B45 124514521",
    "WantsNewsLetter": false,
    "Receipts": [],
    "UsedCoupons": []
  },
  {
    "Name": "asd asd",
    "EMail": "lollern@dragemail.kingking",
    "Password": "qwerty",
    "_PrivateOrCorporation": 1,
    "_AccountType": 2,
    "CVR": "2134",
    "Address": "Banebrinken, 0 K\u00F8benhavn NV",
    "Country": "Denmark",
    "PhoneNumber": "\u002B12 78451268",
    "WantsNewsLetter": false,
    "Receipts": [],
    "UsedCoupons": []
  },
  {
    "Name": "admin admin",
    "EMail": "admin@admin.admin",
    "Password": "admin",
    "_PrivateOrCorporation": 0,
    "_AccountType": 2,
    "CVR": "11111",
    "Address": "et 1, 1111 etterbyen",
    "Country": "etterlandet",
    "PhoneNumber": "\u002B11 11111111",
    "WantsNewsLetter": true,
    "Receipts": [
      "---------------RECEIPT START---------------\n[3] Name Branded Razor - 10 kr.\n[3] Hair gel Other brand Hairgel - 10 kr.\n[2] Hair gsel Other brand Hairgel - 99,99 kr.\n[2] Hsair gel Other brand Hairgel - 99,99 kr.\n---------------RECEIPT END---------------\n",
      "---------------RECEIPT START---------------\n[2] Hair gel Other brand Hairgel - 1337 kr.\n[4] sName Branded Razor - 199,99 kr.\nTotal price: 4342,45\nTax: 3473,96\n---------------RECEIPT END---------------\n",
      "---------------RECEIPT START---------------\n[4] Hair gel Other brand Hairgel - 1337 kr.\n[1] Gel\u0027ler hairs Super brand Hairgel - 119,99 kr.\n[1] Hair gsel Other brand Hairgel - 99,99 kr.\nApplied coupon: CurrentlyAppliedCoupon which gave 100% off\nTotal price: 6959,974999999999\nTax: 5567,98\n---------------RECEIPT END---------------\n",
      "---------------RECEIPT START---------------\n[1] Hair gel Other brand Hairgel - 1337 kr.\n[1] sName Branded Razor - 199,99 kr.\nApplied coupon: 25-Off which gave 25% off\nTotal price: 480,309375\nTax: 384,2475\n---------------RECEIPT END---------------\n"
    ],
    "UsedCoupons": [
      "CurrentlyAppliedCoupon",
      "25-Off"
    ]
  },
  {
    "Name": "User usernamer",
    "EMail": "user@user.user",
    "Password": "users",
    "_PrivateOrCorporation": 0,
    "_AccountType": 0,
    "CVR": null,
    "Address": "et 1, 0 ",
    "Country": "Denmark",
    "PhoneNumber": "11111111",
    "WantsNewsLetter": false,
    "Receipts": [
      "---------------RECEIPT START---------------\n[3] Hair gel Other brand Hairgel - 10 kr.\n[2] Gel\u0027ler hair Super brand Hairgel - 119,99 kr.\n[2] Name Branded Razor - 10 kr.\n[3] Nasme Branded Razor - 199,99 kr.\n[2] Hair gsel Other brand Hairgel - 99,99 kr.\n[3] Expenssive hair gel Branded Hairgel - 1199,99 kr.\n[2] sName Branded Razor - 199,99 kr.\n[3] Hsair gel Other brand Hairgel - 99,99 kr.\n[5] Expensive hairs gel Branded Hairgel - 1199,99 kr.\n[3] Hairs gel Other brand Hairgel - 99,99 kr.\n---------------RECEIPT END---------------\n"
    ],
    "UsedCoupons": []
  },
  {
    "Name": "luffe luffe",
    "EMail": "LuffesEmail@gmail.com",
    "Password": "123456",
    "_PrivateOrCorporation": 0,
    "_AccountType": 0,
    "CVR": null,
    "Address": "aaa vej 90, 4000 Roskilde",
    "Country": "Danmark",
    "PhoneNumber": "\u002B45 98647247",
    "WantsNewsLetter": false,
    "Receipts": [],
    "UsedCoupons": []
  },
  {
    "Name": "Worker Workersen",
    "EMail": "work@non",
    "Password": "worker",
    "_PrivateOrCorporation": 0,
    "_AccountType": 0,
    "CVR": null,
    "Address": "dsa, 2 sssa",
    "Country": "gaswt",
    "PhoneNumber": "\u002B2 31788475",
    "WantsNewsLetter": false,
    "Receipts": [],
    "UsedCoupons": []
  },
  {
    "Name": "Worker Workersen",
    "EMail": "worker@non",
    "Password": "qwerty",
    "_PrivateOrCorporation": 0,
    "_AccountType": 0,
    "CVR": null,
    "Address": "Kongevej, 4000 Roskilde",
    "Country": "Danmark",
    "PhoneNumber": "45 85416375",
    "WantsNewsLetter": false,
    "Receipts": [],
    "UsedCoupons": []
  }
]